{"number_of_variables":130,"number_of_constraints":130,"variable_degree":3,"constraint_degree":3,"rng_seed":4098220472817877359,"graph":{"variable_neighbors":[[10,2,36],[52,74,69],[52,72,15],[27,105,56],[25,33,91],[59,111,62],[18,91,127],[122,20,75],[19,13,66],[94,34,35],[61,43,72],[104,57,66],[8,56,4],[87,125,53],[118,17,4],[31,107,95],[47,89,49],[116,31,10],[82,47,22],[26,117,83],[12,116,118],[116,123,91],[83,93,94],[38,25,30],[92,128,76],[78,129,29],[59,2,60],[64,5,1],[90,14,115],[40,83,106],[117,40,84],[29,93,41],[54,55,24],[13,12,45],[39,6,121],[68,33,51],[28,95,97],[50,57,26],[112,98,70],[53,16,112],[68,99,104],[42,82,23],[32,41,64],[99,73,127],[13,37,1],[63,4,95],[97,44,65],[34,113,117],[89,39,80],[3,46,51],[0,96,23],[70,115,25],[11,58,98],[120,79,27],[109,61,59],[76,72,100],[38,78,100],[128,84,108],[23,129,65],[14,3,86],[17,85,7],[46,74,94],[44,1,128],[85,101,67],[42,75,122],[96,54,41],[125,112,63],[8,126,2],[45,76,100],[129,90,127],[16,7,38],[73,110,22],[24,88,14],[34,96,119],[97,101,39],[18,6,110],[71,82,0],[42,6,105],[84,49,48],[85,126,54],[21,119,110],[58,111,35],[63,43,31],[46,78,43],[45,18,12],[69,67,9],[98,53,87],[86,9,123],[122,121,79],[81,5,114],[69,19,124],[71,108,124],[22,109,62],[102,77,32],[15,20,113],[92,49,77],[60,51,103],[86,113,20],[56,80,33],[66,47,120],[40,27,125],[26,50,55],[5,73,9],[35,103,92],[70,48,44],[52,93,57],[30,126,77],[102,88,115],[68,103,81],[105,11,106],[36,104,55],[106,74,102],[62,80,75],[10,36,3],[107,87,21],[19,37,121],[17,60,118],[90,28,15],[21,16,8],[109,99,79],[30,61,107],[124,120,11],[71,108,65],[29,114,67],[89,0,101],[88,32,48],[7,111,123],[119,24,81],[37,64,50],[28,114,58]],"constraint_neighbors":[[50,124,76],[62,44,27],[26,0,67],[49,59,113],[45,14,12],[102,27,89],[75,77,34],[126,70,60],[12,67,118],[87,85,102],[0,113,17],[52,109,121],[20,33,84],[44,33,8],[59,28,72],[94,117,2],[70,39,118],[116,14,60],[75,6,84],[8,90,115],[7,97,94],[118,80,114],[92,71,18],[58,41,50],[72,32,127],[4,23,51],[19,101,37],[3,100,53],[36,129,117],[31,123,25],[106,120,23],[17,15,82],[42,125,93],[4,35,98],[47,73,9],[103,81,9],[110,113,0],[128,44,115],[70,56,23],[34,48,74],[29,100,30],[42,65,31],[77,64,41],[10,82,83],[62,46,104],[84,68,33],[83,61,49],[16,18,99],[125,104,78],[95,16,78],[37,101,128],[96,35,49],[2,1,105],[39,86,13],[32,79,65],[32,110,101],[98,12,3],[37,11,105],[81,52,129],[5,54,26],[116,96,26],[10,54,120],[112,5,92],[45,66,82],[27,42,128],[58,122,46],[99,11,8],[123,63,85],[35,108,40],[90,85,1],[38,51,104],[76,91,122],[55,2,10],[71,102,43],[61,111,1],[7,64,112],[55,68,24],[93,95,106],[25,83,56],[53,88,119],[112,48,98],[89,127,108],[18,76,41],[22,29,19],[78,57,30],[63,79,60],[97,87,59],[13,86,114],[125,107,72],[48,124,16],[69,28,117],[21,6,4],[24,95,103],[22,31,105],[9,22,61],[15,36,45],[65,73,50],[46,74,36],[38,86,52],[43,40,119],[55,68,56],[63,124,74],[107,93,111],[103,96,108],[11,110,40],[109,77,3],[111,109,29],[114,120,15],[91,57,122],[119,54,92],[71,75,80],[5,126,81],[38,66,39],[47,97,94],[123,129,89],[107,28,51],[17,21,20],[19,47,30],[14,116,20],[127,80,73],[53,121,99],[88,115,34],[7,88,64],[21,87,126],[121,91,90],[66,100,13],[67,106,79],[6,43,69],[57,24,62],[69,25,58]],"edges":[{"variable":14,"constraint":17},{"variable":38,"constraint":112},{"variable":2,"constraint":52},{"variable":66,"constraint":125},{"variable":12,"constraint":8},{"variable":5,"constraint":59},{"variable":38,"constraint":98},{"variable":119,"constraint":109},{"variable":44,"constraint":13},{"variable":20,"constraint":12},{"variable":31,"constraint":29},{"variable":37,"constraint":50},{"variable":48,"constraint":89},{"variable":114,"constraint":107},{"variable":22,"constraint":83},{"variable":42,"constraint":32},{"variable":63,"constraint":85},{"variable":69,"constraint":129},{"variable":18,"constraint":82},{"variable":106,"constraint":30},{"variable":47,"constraint":34},{"variable":13,"constraint":87},{"variable":70,"constraint":16},{"variable":118,"constraint":21},{"variable":0,"constraint":10},{"variable":10,"constraint":61},{"variable":54,"constraint":109},{"variable":107,"constraint":102},{"variable":19,"constraint":26},{"variable":47,"constraint":113},{"variable":25,"constraint":78},{"variable":19,"constraint":117},{"variable":43,"constraint":99},{"variable":29,"constraint":40},{"variable":121,"constraint":124},{"variable":81,"constraint":58},{"variable":3,"constraint":27},{"variable":29,"constraint":83},{"variable":92,"constraint":22},{"variable":75,"constraint":18},{"variable":4,"constraint":25},{"variable":62,"constraint":44},{"variable":84,"constraint":45},{"variable":52,"constraint":11},{"variable":103,"constraint":35},{"variable":127,"constraint":119},{"variable":6,"constraint":18},{"variable":97,"constraint":86},{"variable":24,"constraint":92},{"variable":34,"constraint":39},{"variable":53,"constraint":120},{"variable":32,"constraint":54},{"variable":7,"constraint":122},{"variable":123,"constraint":29},{"variable":69,"constraint":90},{"variable":25,"constraint":129},{"variable":58,"constraint":23},{"variable":77,"constraint":42},{"variable":126,"constraint":7},{"variable":73,"constraint":34},{"variable":79,"constraint":85},{"variable":71,"constraint":73},{"variable":66,"constraint":112},{"variable":102,"constraint":5},{"variable":55,"constraint":76},{"variable":67,"constraint":8},{"variable":123,"constraint":114},{"variable":27,"constraint":64},{"variable":47,"constraint":117},{"variable":78,"constraint":84},{"variable":87,"constraint":86},{"variable":124,"constraint":89},{"variable":45,"constraint":63},{"variable":17,"constraint":116},{"variable":9,"constraint":94},{"variable":89,"constraint":81},{"variable":109,"constraint":105},{"variable":66,"constraint":63},{"variable":120,"constraint":30},{"variable":83,"constraint":46},{"variable":8,"constraint":19},{"variable":64,"constraint":42},{"variable":100,"constraint":40},{"variable":98,"constraint":56},{"variable":125,"constraint":88},{"variable":58,"constraint":129},{"variable":42,"constraint":41},{"variable":54,"constraint":61},{"variable":11,"constraint":104},{"variable":76,"constraint":71},{"variable":123,"constraint":67},{"variable":30,"constraint":117},{"variable":116,"constraint":17},{"variable":39,"constraint":53},{"variable":75,"constraint":6},{"variable":125,"constraint":32},{"variable":5,"constraint":111},{"variable":76,"constraint":82},{"variable":59,"constraint":14},{"variable":84,"constraint":18},{"variable":86,"constraint":98},{"variable":128,"constraint":37},{"variable":7,"constraint":20},{"variable":36,"constraint":28},{"variable":97,"constraint":113},{"variable":32,"constraint":55},{"variable":16,"constraint":47},{"variable":90,"constraint":69},{"variable":55,"constraint":72},{"variable":22,"constraint":93},{"variable":27,"constraint":5},{"variable":33,"constraint":13},{"variable":93,"constraint":102},{"variable":107,"constraint":88},{"variable":21,"constraint":116},{"variable":21,"constraint":123},{"variable":38,"constraint":70},{"variable":91,"constraint":71},{"variable":71,"constraint":110},{"variable":71,"constraint":22},{"variable":97,"constraint":20},{"variable":51,"constraint":70},{"variable":48,"constraint":39},{"variable":42,"constraint":64},{"variable":44,"constraint":37},{"variable":125,"constraint":48},{"variable":2,"constraint":72},{"variable":57,"constraint":128},{"variable":103,"constraint":103},{"variable":35,"constraint":68},{"variable":116,"constraint":60},{"variable":96,"constraint":60},{"variable":14,"constraint":118},{"variable":61,"constraint":46},{"variable":95,"constraint":92},{"variable":91,"constraint":108},{"variable":68,"constraint":45},{"variable":89,"constraint":5},{"variable":52,"constraint":58},{"variable":100,"constraint":27},{"variable":52,"constraint":98},{"variable":17,"constraint":31},{"variable":107,"constraint":115},{"variable":50,"constraint":0},{"variable":108,"constraint":68},{"variable":54,"constraint":59},{"variable":18,"constraint":47},{"variable":113,"constraint":10},{"variable":16,"constraint":89},{"variable":126,"constraint":111},{"variable":116,"constraint":118},{"variable":26,"constraint":59},{"variable":95,"constraint":49},{"variable":53,"constraint":79},{"variable":4,"constraint":33},{"variable":33,"constraint":12},{"variable":129,"constraint":28},{"variable":40,"constraint":68},{"variable":67,"constraint":126},{"variable":28,"constraint":90},{"variable":99,"constraint":66},{"variable":87,"constraint":9},{"variable":72,"constraint":24},{"variable":93,"constraint":77},{"variable":70,"constraint":7},{"variable":21,"constraint":91},{"variable":62,"constraint":1},{"variable":121,"constraint":120},{"variable":57,"constraint":84},{"variable":101,"constraint":26},{"variable":7,"constraint":75},{"variable":91,"constraint":124},{"variable":65,"constraint":96},{"variable":32,"constraint":24},{"variable":106,"constraint":126},{"variable":37,"constraint":57},{"variable":16,"constraint":49},{"variable":49,"constraint":3},{"variable":95,"constraint":77},{"variable":26,"constraint":2},{"variable":58,"constraint":65},{"variable":100,"constraint":125},{"variable":122,"constraint":71},{"variable":111,"constraint":106},{"variable":112,"constraint":62},{"variable":63,"constraint":101},{"variable":40,"constraint":99},{"variable":28,"constraint":14},{"variable":39,"constraint":16},{"variable":86,"constraint":53},{"variable":124,"constraint":0},{"variable":88,"constraint":122},{"variable":79,"constraint":126},{"variable":82,"constraint":63},{"variable":118,"constraint":16},{"variable":77,"constraint":6},{"variable":109,"constraint":11},{"variable":121,"constraint":11},{"variable":90,"constraint":19},{"variable":129,"constraint":114},{"variable":9,"constraint":34},{"variable":12,"constraint":56},{"variable":41,"constraint":42},{"variable":63,"constraint":67},{"variable":94,"constraint":15},{"variable":57,"constraint":108},{"variable":44,"constraint":1},{"variable":118,"constraint":8},{"variable":46,"constraint":97},{"variable":59,"constraint":3},{"variable":79,"constraint":54},{"variable":70,"constraint":38},{"variable":81,"constraint":111},{"variable":127,"constraint":24},{"variable":106,"constraint":77},{"variable":17,"constraint":10},{"variable":34,"constraint":6},{"variable":0,"constraint":2},{"variable":73,"constraint":96},{"variable":28,"constraint":115},{"variable":96,"constraint":51},{"variable":120,"constraint":61},{"variable":64,"constraint":75},{"variable":86,"constraint":87},{"variable":117,"constraint":90},{"variable":74,"constraint":97},{"variable":110,"constraint":36},{"variable":104,"constraint":70},{"variable":90,"constraint":124},{"variable":101,"constraint":50},{"variable":41,"constraint":82},{"variable":45,"constraint":4},{"variable":83,"constraint":78},{"variable":61,"constraint":74},{"variable":80,"constraint":21},{"variable":15,"constraint":31},{"variable":78,"constraint":49},{"variable":110,"constraint":104},{"variable":104,"constraint":48},{"variable":112,"constraint":80},{"variable":115,"constraint":19},{"variable":30,"constraint":40},{"variable":67,"constraint":2},{"variable":56,"constraint":38},{"variable":13,"constraint":125},{"variable":23,"constraint":38},{"variable":23,"constraint":25},{"variable":128,"constraint":64},{"variable":78,"constraint":48},{"variable":1,"constraint":52},{"variable":124,"constraint":101},{"variable":22,"constraint":94},{"variable":41,"constraint":23},{"variable":127,"constraint":81},{"variable":114,"constraint":87},{"variable":65,"constraint":54},{"variable":84,"constraint":12},{"variable":120,"constraint":107},{"variable":50,"constraint":96},{"variable":85,"constraint":69},{"variable":99,"constraint":47},{"variable":77,"constraint":105},{"variable":20,"constraint":116},{"variable":24,"constraint":128},{"variable":46,"constraint":44},{"variable":68,"constraint":76},{"variable":51,"constraint":115},{"variable":10,"constraint":43},{"variable":60,"constraint":17},{"variable":92,"constraint":109},{"variable":11,"constraint":57},{"variable":50,"constraint":23},{"variable":111,"constraint":74},{"variable":122,"constraint":108},{"variable":110,"constraint":55},{"variable":5,"constraint":62},{"variable":82,"constraint":43},{"variable":35,"constraint":33},{"variable":33,"constraint":45},{"variable":14,"constraint":4},{"variable":35,"constraint":51},{"variable":85,"constraint":67},{"variable":11,"constraint":66},{"variable":93,"constraint":32},{"variable":18,"constraint":22},{"variable":113,"constraint":36},{"variable":13,"constraint":53},{"variable":74,"constraint":101},{"variable":85,"constraint":9},{"variable":8,"constraint":13},{"variable":6,"constraint":91},{"variable":122,"constraint":65},{"variable":55,"constraint":100},{"variable":102,"constraint":73},{"variable":89,"constraint":114},{"variable":109,"constraint":106},{"variable":23,"constraint":30},{"variable":6,"constraint":127},{"variable":49,"constraint":46},{"variable":88,"constraint":121},{"variable":46,"constraint":65},{"variable":1,"constraint":74},{"variable":62,"constraint":128},{"variable":12,"constraint":4},{"variable":65,"constraint":41},{"variable":83,"constraint":43},{"variable":19,"constraint":83},{"variable":111,"constraint":102},{"variable":3,"constraint":105},{"variable":53,"constraint":27},{"variable":3,"constraint":56},{"variable":59,"constraint":86},{"variable":26,"constraint":60},{"variable":115,"constraint":37},{"variable":60,"constraint":85},{"variable":114,"constraint":21},{"variable":1,"constraint":69},{"variable":25,"constraint":29},{"variable":8,"constraint":66},{"variable":31,"constraint":93},{"variable":15,"constraint":107},{"variable":76,"constraint":0},{"variable":72,"constraint":88},{"variable":75,"constraint":110},{"variable":30,"constraint":84},{"variable":128,"constraint":50},{"variable":43,"constraint":73},{"variable":4,"constraint":91},{"variable":68,"constraint":100},{"variable":99,"constraint":120},{"variable":82,"constraint":31},{"variable":61,"constraint":94},{"variable":119,"constraint":99},{"variable":27,"constraint":1},{"variable":87,"constraint":123},{"variable":112,"constraint":75},{"variable":117,"constraint":28},{"variable":126,"constraint":123},{"variable":49,"constraint":51},{"variable":105,"constraint":52},{"variable":104,"constraint":44},{"variable":15,"constraint":95},{"variable":20,"constraint":118},{"variable":36,"constraint":95},{"variable":115,"constraint":121},{"variable":80,"constraint":119},{"variable":45,"constraint":95},{"variable":129,"constraint":58},{"variable":81,"constraint":35},{"variable":40,"constraint":104},{"variable":96,"constraint":103},{"variable":60,"constraint":7},{"variable":43,"constraint":127},{"variable":92,"constraint":62},{"variable":10,"constraint":72},{"variable":34,"constraint":121},{"variable":117,"constraint":15},{"variable":2,"constraint":15},{"variable":9,"constraint":35},{"variable":80,"constraint":110},{"variable":64,"constraint":122},{"variable":108,"constraint":103},{"variable":48,"constraint":80},{"variable":74,"constraint":39},{"variable":0,"constraint":36},{"variable":31,"constraint":41},{"variable":88,"constraint":79},{"variable":29,"constraint":106},{"variable":102,"constraint":9},{"variable":69,"constraint":127},{"variable":108,"constraint":81},{"variable":119,"constraint":79},{"variable":36,"constraint":97},{"variable":101,"constraint":55},{"variable":113,"constraint":3},{"variable":94,"constraint":20},{"variable":103,"constraint":92},{"variable":51,"constraint":25},{"variable":72,"constraint":14},{"variable":73,"constraint":119},{"variable":37,"constraint":26},{"variable":98,"constraint":80},{"variable":56,"constraint":78},{"variable":39,"constraint":112},{"variable":105,"constraint":93},{"variable":24,"constraint":76},{"variable":94,"constraint":113},{"variable":56,"constraint":100},{"variable":98,"constraint":33},{"variable":105,"constraint":57}]}}