{"number_of_variables":44,"number_of_constraints":44,"variable_degree":3,"constraint_degree":3,"rng_seed":6544659830262448721,"graph":{"variable_neighbors":[[21,3,30],[31,15,19],[0,1,20],[40,14,8],[41,33,34],[26,11,35],[13,25,28],[5,24,36],[9,8,14],[3,34,0],[10,15,42],[38,17,24],[33,12,41],[5,32,39],[21,37,20],[32,9,41],[43,13,19],[18,16,13],[22,36,39],[35,1,6],[38,26,27],[23,22,34],[4,31,30],[16,1,12],[32,25,18],[29,7,43],[10,2,35],[7,3,6],[2,27,40],[18,29,16],[12,26,9],[39,42,15],[4,22,6],[38,23,30],[23,33,25],[21,31,27],[42,20,17],[10,8,5],[37,28,29],[11,19,40],[28,36,24],[0,14,2],[43,11,7],[37,4,17]],"constraint_neighbors":[[41,2,9],[2,19,23],[28,26,41],[9,0,27],[32,22,43],[13,7,37],[19,32,27],[27,42,25],[8,37,3],[8,15,30],[10,26,37],[39,5,42],[30,12,23],[6,16,17],[41,8,3],[10,1,31],[23,29,17],[36,11,43],[29,17,24],[39,16,1],[36,2,14],[0,35,14],[21,32,18],[34,33,21],[40,7,11],[6,34,24],[20,5,30],[20,28,35],[40,6,38],[29,38,25],[33,0,22],[1,35,22],[15,13,24],[4,12,34],[4,9,21],[19,26,5],[40,7,18],[38,14,43],[20,33,11],[13,31,18],[3,28,39],[4,12,15],[10,36,31],[42,16,25]],"edges":[{"variable":40,"constraint":36},{"variable":20,"constraint":38},{"variable":34,"constraint":23},{"variable":10,"constraint":10},{"variable":8,"constraint":9},{"variable":15,"constraint":32},{"variable":8,"constraint":8},{"variable":40,"constraint":28},{"variable":20,"constraint":26},{"variable":3,"constraint":40},{"variable":29,"constraint":18},{"variable":26,"constraint":10},{"variable":39,"constraint":11},{"variable":23,"constraint":16},{"variable":32,"constraint":4},{"variable":9,"constraint":3},{"variable":42,"constraint":43},{"variable":33,"constraint":38},{"variable":28,"constraint":2},{"variable":0,"constraint":21},{"variable":1,"constraint":31},{"variable":6,"constraint":13},{"variable":13,"constraint":5},{"variable":6,"constraint":25},{"variable":10,"constraint":15},{"variable":17,"constraint":18},{"variable":4,"constraint":41},{"variable":41,"constraint":0},{"variable":33,"constraint":23},{"variable":41,"constraint":14},{"variable":2,"constraint":0},{"variable":21,"constraint":23},{"variable":29,"constraint":29},{"variable":15,"constraint":9},{"variable":20,"constraint":27},{"variable":10,"constraint":42},{"variable":30,"constraint":12},{"variable":21,"constraint":22},{"variable":19,"constraint":35},{"variable":16,"constraint":43},{"variable":33,"constraint":30},{"variable":4,"constraint":33},{"variable":36,"constraint":42},{"variable":13,"constraint":32},{"variable":39,"constraint":19},{"variable":37,"constraint":10},{"variable":13,"constraint":39},{"variable":16,"constraint":13},{"variable":32,"constraint":22},{"variable":22,"constraint":4},{"variable":12,"constraint":33},{"variable":38,"constraint":37},{"variable":1,"constraint":15},{"variable":31,"constraint":39},{"variable":2,"constraint":1},{"variable":0,"constraint":3},{"variable":27,"constraint":7},{"variable":24,"constraint":32},{"variable":35,"constraint":21},{"variable":28,"constraint":27},{"variable":36,"constraint":20},{"variable":8,"constraint":14},{"variable":6,"constraint":28},{"variable":36,"constraint":17},{"variable":31,"constraint":42},{"variable":37,"constraint":8},{"variable":26,"constraint":2},{"variable":4,"constraint":34},{"variable":12,"constraint":12},{"variable":28,"constraint":40},{"variable":11,"constraint":38},{"variable":26,"constraint":35},{"variable":11,"constraint":17},{"variable":38,"constraint":28},{"variable":19,"constraint":1},{"variable":14,"constraint":21},{"variable":40,"constraint":24},{"variable":19,"constraint":6},{"variable":2,"constraint":20},{"variable":32,"constraint":6},{"variable":18,"constraint":22},{"variable":23,"constraint":1},{"variable":7,"constraint":5},{"variable":7,"constraint":24},{"variable":35,"constraint":31},{"variable":5,"constraint":26},{"variable":9,"constraint":34},{"variable":34,"constraint":33},{"variable":3,"constraint":14},{"variable":5,"constraint":11},{"variable":35,"constraint":27},{"variable":34,"constraint":25},{"variable":38,"constraint":29},{"variable":30,"constraint":26},{"variable":29,"constraint":16},{"variable":30,"constraint":9},{"variable":14,"constraint":37},{"variable":14,"constraint":20},{"variable":22,"constraint":31},{"variable":27,"constraint":3},{"variable":43,"constraint":37},{"variable":31,"constraint":15},{"variable":17,"constraint":16},{"variable":11,"constraint":24},{"variable":25,"constraint":29},{"variable":42,"constraint":11},{"variable":41,"constraint":2},{"variable":24,"constraint":25},{"variable":42,"constraint":7},{"variable":7,"constraint":36},{"variable":3,"constraint":8},{"variable":17,"constraint":13},{"variable":43,"constraint":4},{"variable":12,"constraint":41},{"variable":9,"constraint":0},{"variable":0,"constraint":30},{"variable":15,"constraint":41},{"variable":23,"constraint":12},{"variable":16,"constraint":19},{"variable":5,"constraint":35},{"variable":27,"constraint":6},{"variable":1,"constraint":19},{"variable":18,"constraint":36},{"variable":37,"constraint":5},{"variable":43,"constraint":17},{"variable":39,"constraint":40},{"variable":21,"constraint":34},{"variable":25,"constraint":7},{"variable":25,"constraint":43},{"variable":24,"constraint":18},{"variable":22,"constraint":30},{"variable":18,"constraint":39}]}}