{"number_of_variables":80,"number_of_constraints":80,"variable_degree":3,"constraint_degree":3,"rng_seed":12678283139806656634,"graph":{"variable_neighbors":[[13,50,52],[76,35,58],[59,60,75],[73,10,62],[37,9,19],[56,43,12],[74,12,31],[42,11,63],[24,48,64],[29,21,7],[27,20,55],[77,13,17],[33,1,64],[14,6,8],[21,15,44],[63,42,3],[44,45,6],[14,46,51],[67,22,29],[54,3,47],[77,18,70],[1,78,54],[53,65,27],[22,35,56],[61,59,41],[16,36,45],[58,77,9],[5,3,17],[63,35,25],[70,36,76],[73,67,57],[62,1,59],[33,68,65],[29,68,22],[2,20,14],[34,72,75],[24,40,26],[61,11,5],[8,15,41],[51,4,32],[18,60,2],[53,60,39],[8,30,4],[46,66,0],[10,76,26],[19,6,56],[34,50,49],[78,46,74],[48,23,49],[78,71,79],[58,25,16],[37,71,68],[42,4,55],[44,57,41],[55,5,62],[64,0,79],[38,9,66],[69,28,49],[31,71,24],[27,40,53],[39,66,43],[54,73,34],[7,33,40],[32,47,17],[11,30,36],[23,38,70],[10,20,12],[38,37,28],[2,13,25],[69,30,39],[52,72,75],[23,16,7],[48,72,67],[51,21,52],[50,57,26],[45,65,79],[69,28,18],[43,31,61],[15,74,19],[32,47,0]],"constraint_neighbors":[[79,55,43],[21,31,12],[34,68,40],[19,15,27],[39,52,42],[27,54,37],[16,45,13],[62,71,9],[38,42,13],[4,56,26],[44,66,3],[64,37,7],[6,66,5],[0,68,11],[17,13,34],[14,38,78],[25,71,50],[11,27,63],[40,20,76],[45,4,78],[34,66,10],[14,73,9],[23,18,33],[65,71,48],[36,8,58],[68,50,28],[44,74,36],[59,10,22],[57,76,67],[9,33,18],[69,64,42],[77,58,6],[79,63,39],[32,12,62],[35,46,61],[1,23,28],[25,64,29],[4,51,67],[56,67,65],[60,41,69],[59,62,36],[24,53,38],[52,7,15],[77,5,60],[16,14,53],[75,16,25],[47,43,17],[79,63,19],[72,48,8],[57,46,48],[0,74,46],[39,73,17],[0,70,73],[22,41,59],[19,21,61],[54,10,52],[5,23,45],[30,53,74],[26,50,1],[2,24,31],[2,40,41],[37,24,77],[31,3,54],[28,15,7],[55,12,8],[75,32,22],[60,43,56],[30,18,72],[32,33,51],[57,76,69],[20,29,65],[49,58,51],[72,70,35],[30,3,61],[47,6,78],[2,35,70],[1,44,29],[20,11,26],[47,49,21],[49,75,55]],"edges":[{"variable":25,"constraint":45},{"variable":36,"constraint":24},{"variable":77,"constraint":43},{"variable":4,"constraint":37},{"variable":65,"constraint":23},{"variable":60,"constraint":39},{"variable":9,"constraint":29},{"variable":26,"constraint":58},{"variable":47,"constraint":78},{"variable":56,"constraint":38},{"variable":44,"constraint":10},{"variable":14,"constraint":21},{"variable":1,"constraint":76},{"variable":72,"constraint":48},{"variable":79,"constraint":32},{"variable":0,"constraint":13},{"variable":32,"constraint":33},{"variable":49,"constraint":78},{"variable":28,"constraint":63},{"variable":77,"constraint":31},{"variable":22,"constraint":53},{"variable":25,"constraint":16},{"variable":37,"constraint":61},{"variable":59,"constraint":27},{"variable":39,"constraint":51},{"variable":20,"constraint":77},{"variable":25,"constraint":36},{"variable":73,"constraint":51},{"variable":15,"constraint":63},{"variable":57,"constraint":69},{"variable":40,"constraint":18},{"variable":72,"constraint":72},{"variable":79,"constraint":47},{"variable":0,"constraint":50},{"variable":5,"constraint":56},{"variable":75,"constraint":45},{"variable":58,"constraint":31},{"variable":30,"constraint":73},{"variable":64,"constraint":11},{"variable":34,"constraint":2},{"variable":2,"constraint":59},{"variable":30,"constraint":67},{"variable":51,"constraint":37},{"variable":16,"constraint":44},{"variable":60,"constraint":66},{"variable":73,"constraint":21},{"variable":57,"constraint":28},{"variable":71,"constraint":23},{"variable":23,"constraint":22},{"variable":0,"constraint":52},{"variable":59,"constraint":40},{"variable":12,"constraint":33},{"variable":79,"constraint":0},{"variable":47,"constraint":46},{"variable":31,"constraint":62},{"variable":55,"constraint":64},{"variable":17,"constraint":14},{"variable":44,"constraint":76},{"variable":14,"constraint":15},{"variable":52,"constraint":42},{"variable":44,"constraint":26},{"variable":18,"constraint":67},{"variable":19,"constraint":54},{"variable":24,"constraint":61},{"variable":31,"constraint":1},{"variable":35,"constraint":34},{"variable":68,"constraint":2},{"variable":43,"constraint":46},{"variable":27,"constraint":5},{"variable":14,"constraint":44},{"variable":20,"constraint":18},{"variable":7,"constraint":42},{"variable":18,"constraint":22},{"variable":43,"constraint":66},{"variable":1,"constraint":35},{"variable":63,"constraint":32},{"variable":39,"constraint":4},{"variable":68,"constraint":13},{"variable":54,"constraint":55},{"variable":37,"constraint":11},{"variable":76,"constraint":69},{"variable":55,"constraint":0},{"variable":76,"constraint":28},{"variable":32,"constraint":68},{"variable":49,"constraint":71},{"variable":19,"constraint":3},{"variable":46,"constraint":34},{"variable":30,"constraint":57},{"variable":15,"constraint":42},{"variable":2,"constraint":60},{"variable":68,"constraint":25},{"variable":58,"constraint":71},{"variable":8,"constraint":24},{"variable":70,"constraint":52},{"variable":39,"constraint":32},{"variable":48,"constraint":48},{"variable":70,"constraint":72},{"variable":11,"constraint":77},{"variable":17,"constraint":46},{"variable":48,"constraint":23},{"variable":7,"constraint":11},{"variable":21,"constraint":1},{"variable":62,"constraint":7},{"variable":53,"constraint":44},{"variable":8,"constraint":48},{"variable":33,"constraint":29},{"variable":69,"constraint":69},{"variable":9,"constraint":21},{"variable":12,"constraint":1},{"variable":62,"constraint":33},{"variable":66,"constraint":10},{"variable":40,"constraint":60},{"variable":10,"constraint":27},{"variable":75,"constraint":65},{"variable":50,"constraint":58},{"variable":21,"constraint":78},{"variable":67,"constraint":38},{"variable":42,"constraint":8},{"variable":11,"constraint":13},{"variable":41,"constraint":53},{"variable":26,"constraint":77},{"variable":74,"constraint":50},{"variable":3,"constraint":73},{"variable":41,"constraint":60},{"variable":63,"constraint":47},{"variable":38,"constraint":8},{"variable":51,"constraint":71},{"variable":45,"constraint":19},{"variable":13,"constraint":14},{"variable":69,"constraint":30},{"variable":4,"constraint":9},{"variable":34,"constraint":20},{"variable":76,"constraint":18},{"variable":40,"constraint":2},{"variable":23,"constraint":35},{"variable":47,"constraint":74},{"variable":67,"constraint":37},{"variable":20,"constraint":70},{"variable":64,"constraint":30},{"variable":66,"constraint":20},{"variable":62,"constraint":40},{"variable":24,"constraint":59},{"variable":15,"constraint":3},{"variable":72,"constraint":67},{"variable":24,"constraint":41},{"variable":5,"constraint":43},{"variable":2,"constraint":75},{"variable":54,"constraint":5},{"variable":16,"constraint":45},{"variable":35,"constraint":72},{"variable":4,"constraint":19},{"variable":73,"constraint":52},{"variable":49,"constraint":79},{"variable":6,"constraint":74},{"variable":59,"constraint":53},{"variable":32,"constraint":65},{"variable":42,"constraint":30},{"variable":53,"constraint":57},{"variable":75,"constraint":79},{"variable":29,"constraint":70},{"variable":21,"constraint":54},{"variable":16,"constraint":6},{"variable":52,"constraint":4},{"variable":7,"constraint":63},{"variable":56,"constraint":9},{"variable":26,"constraint":9},{"variable":53,"constraint":41},{"variable":64,"constraint":36},{"variable":55,"constraint":79},{"variable":10,"constraint":20},{"variable":71,"constraint":16},{"variable":43,"constraint":0},{"variable":12,"constraint":64},{"variable":6,"constraint":12},{"variable":71,"constraint":7},{"variable":61,"constraint":54},{"variable":36,"constraint":40},{"variable":35,"constraint":75},{"variable":9,"constraint":7},{"variable":23,"constraint":56},{"variable":22,"constraint":65},{"variable":74,"constraint":57},{"variable":74,"constraint":26},{"variable":38,"constraint":15},{"variable":45,"constraint":6},{"variable":60,"constraint":43},{"variable":70,"constraint":75},{"variable":31,"constraint":59},{"variable":10,"constraint":55},{"variable":66,"constraint":12},{"variable":58,"constraint":24},{"variable":13,"constraint":6},{"variable":50,"constraint":25},{"variable":65,"constraint":38},{"variable":3,"constraint":10},{"variable":6,"constraint":31},{"variable":37,"constraint":5},{"variable":8,"constraint":64},{"variable":38,"constraint":41},{"variable":42,"constraint":4},{"variable":45,"constraint":56},{"variable":33,"constraint":68},{"variable":13,"constraint":8},{"variable":34,"constraint":14},{"variable":57,"constraint":49},{"variable":41,"constraint":39},{"variable":61,"constraint":73},{"variable":65,"constraint":70},{"variable":67,"constraint":28},{"variable":61,"constraint":34},{"variable":50,"constraint":16},{"variable":11,"constraint":17},{"variable":46,"constraint":50},{"variable":3,"constraint":62},{"variable":77,"constraint":61},{"variable":54,"constraint":62},{"variable":36,"constraint":26},{"variable":28,"constraint":35},{"variable":17,"constraint":51},{"variable":29,"constraint":36},{"variable":78,"constraint":15},{"variable":78,"constraint":74},{"variable":51,"constraint":68},{"variable":46,"constraint":49},{"variable":69,"constraint":39},{"variable":52,"constraint":55},{"variable":27,"constraint":3},{"variable":48,"constraint":49},{"variable":33,"constraint":22},{"variable":28,"constraint":25},{"variable":29,"constraint":76},{"variable":27,"constraint":17},{"variable":18,"constraint":29},{"variable":5,"constraint":12},{"variable":63,"constraint":17},{"variable":56,"constraint":66},{"variable":19,"constraint":47},{"variable":1,"constraint":58},{"variable":78,"constraint":19},{"variable":22,"constraint":27}]}}