{"number_of_variables":100,"number_of_constraints":100,"variable_degree":3,"constraint_degree":3,"rng_seed":631747622548338813,"graph":{"variable_neighbors":[[88,57,30],[75,58,14],[56,71,96],[87,93,97],[27,29,95],[2,91,62],[49,87,14],[59,60,34],[31,15,79],[95,0,29],[10,70,42],[66,33,22],[46,94,73],[52,13,98],[47,38,16],[2,74,40],[33,58,37],[75,18,50],[19,56,88],[23,33,54],[69,53,30],[84,38,57],[70,69,81],[31,77,48],[82,44,83],[82,13,22],[69,76,80],[81,90,68],[5,44,86],[72,86,99],[77,8,5],[20,82,26],[58,10,11],[95,53,62],[48,80,16],[61,71,46],[7,90,19],[96,65,21],[72,18,89],[36,52,57],[65,24,21],[94,59,49],[3,35,51],[9,43,53],[13,63,67],[81,25,64],[3,39,19],[28,6,39],[50,11,97],[43,12,7],[79,20,72],[21,80,89],[39,15,41],[73,96,28],[17,42,94],[78,45,76],[68,84,17],[41,23,66],[26,41,25],[75,24,48],[74,40,2],[54,66,28],[46,42,60],[6,8,35],[22,61,92],[61,83,0],[68,12,36],[55,60,64],[64,10,23],[67,36,63],[27,85,20],[89,78,63],[12,97,14],[45,16,32],[18,50,85],[62,91,7],[51,77,34],[44,98,55],[70,6,98],[1,24,11],[74,47,45],[32,1,92],[1,15,73],[25,79,4],[9,17,27],[43,3,47],[5,54,92],[37,9,59],[56,35,83],[88,49,30],[93,55,31],[0,84,8],[4,52,99],[40,37,38],[99,4,34],[71,91,85],[87,29,26],[51,90,78],[65,67,93],[32,76,86]],"constraint_neighbors":[[9,65,91],[82,79,81],[15,5,60],[42,85,46],[92,94,83],[86,28,30],[47,63,78],[36,49,75],[30,63,91],[43,84,87],[10,32,68],[79,32,48],[72,66,49],[44,25,13],[6,1,72],[52,82,8],[73,14,34],[54,84,56],[38,17,74],[18,46,36],[31,50,70],[51,37,40],[64,11,25],[57,19,68],[79,40,59],[83,45,58],[31,58,96],[4,70,84],[47,53,61],[4,96,9],[20,0,89],[23,8,90],[81,73,99],[16,11,19],[94,7,76],[42,88,63],[39,66,69],[93,87,16],[14,21,93],[52,46,47],[93,15,60],[57,58,52],[62,54,10],[85,43,49],[77,24,28],[73,80,55],[62,12,35],[14,80,85],[34,23,59],[41,6,89],[74,48,17],[97,76,42],[39,92,13],[33,20,43],[61,86,19],[67,90,77],[88,18,2],[0,39,21],[32,16,1],[41,7,87],[7,67,62],[65,35,64],[75,33,5],[71,44,69],[68,45,67],[98,37,40],[11,61,57],[98,69,44],[66,56,27],[26,20,22],[22,78,10],[95,35,2],[29,38,50],[53,82,12],[15,80,60],[17,1,59],[26,55,99],[30,23,76],[55,71,97],[83,50,8],[26,51,34],[45,27,22],[25,24,31],[65,24,88],[21,56,91],[95,70,74],[29,99,28],[3,96,6],[0,89,18],[71,51,38],[97,27,36],[95,75,5],[86,64,81],[90,3,98],[41,12,54],[33,9,4],[37,53,2],[72,3,48],[78,77,13],[94,29,92]],"edges":[{"variable":5,"constraint":62},{"variable":71,"constraint":89},{"variable":15,"constraint":2},{"variable":26,"constraint":69},{"variable":72,"constraint":12},{"variable":45,"constraint":81},{"variable":20,"constraint":69},{"variable":21,"constraint":84},{"variable":33,"constraint":95},{"variable":88,"constraint":56},{"variable":67,"constraint":55},{"variable":9,"constraint":95},{"variable":93,"constraint":40},{"variable":93,"constraint":37},{"variable":43,"constraint":9},{"variable":65,"constraint":61},{"variable":4,"constraint":27},{"variable":42,"constraint":3},{"variable":85,"constraint":43},{"variable":75,"constraint":62},{"variable":11,"constraint":66},{"variable":82,"constraint":1},{"variable":29,"constraint":72},{"variable":33,"constraint":53},{"variable":0,"constraint":88},{"variable":31,"constraint":20},{"variable":33,"constraint":62},{"variable":94,"constraint":99},{"variable":17,"constraint":75},{"variable":23,"constraint":31},{"variable":41,"constraint":94},{"variable":41,"constraint":59},{"variable":3,"constraint":87},{"variable":22,"constraint":70},{"variable":97,"constraint":51},{"variable":72,"constraint":97},{"variable":14,"constraint":47},{"variable":83,"constraint":25},{"variable":4,"constraint":29},{"variable":95,"constraint":71},{"variable":79,"constraint":1},{"variable":35,"constraint":61},{"variable":83,"constraint":79},{"variable":92,"constraint":4},{"variable":20,"constraint":53},{"variable":37,"constraint":96},{"variable":38,"constraint":72},{"variable":68,"constraint":64},{"variable":16,"constraint":33},{"variable":27,"constraint":81},{"variable":78,"constraint":70},{"variable":87,"constraint":37},{"variable":7,"constraint":59},{"variable":98,"constraint":65},{"variable":7,"constraint":60},{"variable":43,"constraint":43},{"variable":64,"constraint":22},{"variable":0,"constraint":57},{"variable":86,"constraint":5},{"variable":67,"constraint":60},{"variable":62,"constraint":46},{"variable":18,"constraint":19},{"variable":26,"constraint":76},{"variable":89,"constraint":88},{"variable":51,"constraint":21},{"variable":73,"constraint":45},{"variable":41,"constraint":49},{"variable":34,"constraint":48},{"variable":37,"constraint":65},{"variable":61,"constraint":54},{"variable":35,"constraint":71},{"variable":38,"constraint":18},{"variable":97,"constraint":90},{"variable":10,"constraint":10},{"variable":9,"constraint":0},{"variable":79,"constraint":24},{"variable":32,"constraint":58},{"variable":47,"constraint":28},{"variable":6,"constraint":49},{"variable":84,"constraint":9},{"variable":14,"constraint":38},{"variable":39,"constraint":36},{"variable":11,"constraint":33},{"variable":45,"constraint":25},{"variable":54,"constraint":17},{"variable":15,"constraint":74},{"variable":32,"constraint":10},{"variable":95,"constraint":91},{"variable":66,"constraint":68},{"variable":26,"constraint":80},{"variable":17,"constraint":18},{"variable":47,"constraint":6},{"variable":1,"constraint":75},{"variable":57,"constraint":41},{"variable":25,"constraint":82},{"variable":79,"constraint":11},{"variable":4,"constraint":95},{"variable":30,"constraint":8},{"variable":65,"constraint":83},{"variable":43,"constraint":53},{"variable":53,"constraint":73},{"variable":73,"constraint":16},{"variable":85,"constraint":3},{"variable":98,"constraint":67},{"variable":63,"constraint":6},{"variable":42,"constraint":35},{"variable":37,"constraint":21},{"variable":77,"constraint":44},{"variable":49,"constraint":43},{"variable":28,"constraint":5},{"variable":95,"constraint":85},{"variable":45,"constraint":64},{"variable":90,"constraint":93},{"variable":62,"constraint":42},{"variable":39,"constraint":52},{"variable":81,"constraint":32},{"variable":78,"constraint":6},{"variable":96,"constraint":87},{"variable":80,"constraint":74},{"variable":18,"constraint":56},{"variable":30,"constraint":77},{"variable":2,"constraint":56},{"variable":16,"constraint":58},{"variable":52,"constraint":39},{"variable":66,"constraint":12},{"variable":94,"constraint":4},{"variable":66,"constraint":36},{"variable":76,"constraint":51},{"variable":29,"constraint":86},{"variable":87,"constraint":9},{"variable":55,"constraint":78},{"variable":2,"constraint":71},{"variable":78,"constraint":98},{"variable":22,"constraint":69},{"variable":3,"constraint":93},{"variable":71,"constraint":78},{"variable":24,"constraint":82},{"variable":52,"constraint":15},{"variable":56,"constraint":68},{"variable":3,"constraint":97},{"variable":50,"constraint":79},{"variable":63,"constraint":8},{"variable":6,"constraint":87},{"variable":39,"constraint":57},{"variable":84,"constraint":17},{"variable":44,"constraint":13},{"variable":29,"constraint":99},{"variable":46,"constraint":3},{"variable":24,"constraint":44},{"variable":57,"constraint":23},{"variable":6,"constraint":14},{"variable":64,"constraint":61},{"variable":88,"constraint":35},{"variable":61,"constraint":66},{"variable":73,"constraint":32},{"variable":90,"constraint":55},{"variable":69,"constraint":67},{"variable":70,"constraint":27},{"variable":1,"constraint":58},{"variable":31,"constraint":82},{"variable":5,"constraint":2},{"variable":12,"constraint":46},{"variable":80,"constraint":47},{"variable":59,"constraint":75},{"variable":23,"constraint":77},{"variable":86,"constraint":54},{"variable":30,"constraint":5},{"variable":20,"constraint":30},{"variable":50,"constraint":20},{"variable":1,"constraint":14},{"variable":96,"constraint":29},{"variable":19,"constraint":23},{"variable":40,"constraint":65},{"variable":77,"constraint":98},{"variable":62,"constraint":60},{"variable":0,"constraint":30},{"variable":67,"constraint":64},{"variable":81,"constraint":1},{"variable":51,"constraint":80},{"variable":28,"constraint":44},{"variable":19,"constraint":33},{"variable":27,"constraint":90},{"variable":65,"constraint":0},{"variable":89,"constraint":49},{"variable":74,"constraint":18},{"variable":46,"constraint":39},{"variable":80,"constraint":45},{"variable":74,"constraint":50},{"variable":23,"constraint":48},{"variable":31,"constraint":26},{"variable":94,"constraint":34},{"variable":54,"constraint":42},{"variable":36,"constraint":7},{"variable":86,"constraint":92},{"variable":55,"constraint":45},{"variable":84,"constraint":27},{"variable":32,"constraint":11},{"variable":71,"constraint":63},{"variable":49,"constraint":12},{"variable":24,"constraint":83},{"variable":92,"constraint":52},{"variable":9,"constraint":29},{"variable":15,"constraint":40},{"variable":58,"constraint":26},{"variable":8,"constraint":31},{"variable":60,"constraint":74},{"variable":48,"constraint":50},{"variable":42,"constraint":51},{"variable":68,"constraint":10},{"variable":70,"constraint":85},{"variable":83,"constraint":4},{"variable":51,"constraint":89},{"variable":27,"constraint":68},{"variable":46,"constraint":19},{"variable":47,"constraint":39},{"variable":7,"constraint":34},{"variable":18,"constraint":88},{"variable":69,"constraint":36},{"variable":53,"constraint":96},{"variable":99,"constraint":32},{"variable":49,"constraint":7},{"variable":82,"constraint":15},{"variable":82,"constraint":73},{"variable":56,"constraint":84},{"variable":77,"constraint":55},{"variable":16,"constraint":37},{"variable":2,"constraint":96},{"variable":36,"constraint":90},{"variable":76,"constraint":77},{"variable":13,"constraint":52},{"variable":75,"constraint":91},{"variable":57,"constraint":66},{"variable":10,"constraint":70},{"variable":56,"constraint":17},{"variable":68,"constraint":23},{"variable":12,"constraint":94},{"variable":70,"constraint":20},{"variable":17,"constraint":50},{"variable":40,"constraint":24},{"variable":64,"constraint":92},{"variable":53,"constraint":28},{"variable":50,"constraint":72},{"variable":40,"constraint":21},{"variable":60,"constraint":40},{"variable":44,"constraint":63},{"variable":21,"constraint":38},{"variable":19,"constraint":54},{"variable":59,"constraint":24},{"variable":74,"constraint":85},{"variable":34,"constraint":80},{"variable":35,"constraint":46},{"variable":90,"constraint":31},{"variable":75,"constraint":7},{"variable":59,"constraint":48},{"variable":88,"constraint":83},{"variable":55,"constraint":76},{"variable":60,"constraint":2},{"variable":48,"constraint":11},{"variable":44,"constraint":67},{"variable":87,"constraint":59},{"variable":11,"constraint":22},{"variable":63,"constraint":35},{"variable":97,"constraint":78},{"variable":14,"constraint":16},{"variable":36,"constraint":19},{"variable":10,"constraint":42},{"variable":98,"constraint":93},{"variable":25,"constraint":13},{"variable":13,"constraint":13},{"variable":89,"constraint":30},{"variable":8,"constraint":15},{"variable":81,"constraint":92},{"variable":38,"constraint":89},{"variable":22,"constraint":81},{"variable":5,"constraint":91},{"variable":25,"constraint":22},{"variable":92,"constraint":99},{"variable":99,"constraint":76},{"variable":61,"constraint":28},{"variable":34,"constraint":16},{"variable":58,"constraint":41},{"variable":13,"constraint":98},{"variable":91,"constraint":0},{"variable":72,"constraint":14},{"variable":93,"constraint":38},{"variable":52,"constraint":41},{"variable":99,"constraint":86},{"variable":48,"constraint":97},{"variable":76,"constraint":34},{"variable":96,"constraint":26},{"variable":12,"constraint":73},{"variable":8,"constraint":79},{"variable":21,"constraint":57},{"variable":91,"constraint":84},{"variable":58,"constraint":25},{"variable":54,"constraint":94},{"variable":69,"constraint":63},{"variable":85,"constraint":47},{"variable":91,"constraint":8},{"variable":28,"constraint":86}]}}